{"0x506404": "系统内部软件时间片超时", "0x505049": "ram检查错误", "0x506549": "PCU无法关闭低边驱动电路", "0x505005": "软件释放版本不正确", "0x505044": "Eeprom存储器故障", "0x505149": "FMON无法控制驱动电路", "0x403118": "左前轮轮速传感器故障（通用）", "0x40312f": "左前轮轮速传感器故障（电极错误）", "0x403137": "左前轮轮速传感器故障（频率过高）", "0x403162": "左前轮轮速传感器故障（频率过低）", "0x403197": "左前轮ABS作动时间过长", "0x403029": "左前轮轮速传感器故障（干扰）", "0x403164": "左前轮轮速传感器故障（方向错误）", "0x403129": "左前轮轮速传感器故障（噪声）", "0x403418": "右前轮轮速传感器故障（通用）", "0x40342f": "右前轮轮速传感器故障（电极错误）", "0x403437": "右前轮轮速传感器故障（频率过高）", "0x403462": "右前轮轮速传感器故障（频率过低）", "0x403497": "右前轮ABS作动时间过长", "0x403329": "右前轮轮速传感器故障（干扰）", "0x403464": "右前轮轮速传感器故障（方向错误）", "0x403429": "右前轮轮速传感器故障（噪声）", "0x403718": "左后轮轮速传感器故障（通用）", "0x40372f": "左后轮轮速传感器故障（电极错误）", "0x403737": "左后轮轮速传感器故障（频率过高）", "0x403762": "左后轮轮速传感器故障（频率过低）", "0x403797": "左后轮ABS作动时间过长", "0x403629": "左后轮轮速传感器故障（干扰）", "0x403764": "左后轮轮速传感器故障（方向错误）", "0x403729": "左后轮轮速传感器故障（噪声）", "0x403a18": "右后轮轮速传感器故障（通用）", "0x403a2f": "右后轮轮速传感器故障（电极错误）", "0x403a37": "右后轮轮速传感器故障（频率过高）", "0x403a62": "右后轮轮速传感器故障（频率过低）", "0x403a97": "右后轮ABS作动时间过长", "0x403929": "右后轮轮速传感器故障（干扰）", "0x403a64": "右后轮轮速传感器故障（方向错误）", "0x403a29": "右后轮轮速传感器故障（噪声）", "0x402016": "泵状态异常（空闲时）", "0x402071": "泵电机发电机电压过低", "0x402013": "泵电机供应电压过低", "0x402011": "泵电路短路", "0x402012": "泵电路断路", "0x401001": "左前常开阀错误", "0x401401": "右前常开阀错误", "0x401801": "左后常开阀错误", "0x401c01": "右后常开阀错误", "0x401101": "左前常闭阀错误", "0x401501": "右前常闭阀错误", "0x401901": "左后常闭阀错误", "0x401d01": "右后常闭阀错误", "0x505201": "主缸压力阀1错误", "0x505301": "主缸压力阀2错误", "0x505401": "电子换向阀1错误", "0x505501": "电子换向阀2错误", "0x505616": "ECU供电电压低于阈值", "0x505617": "ECU供电电压超出阈值", "0x406b00": "AYC工作时间过长", "0x505754": "阀标定数据不完整", "0x404064": "刹车灯开关信号不正常", "0x505864": "ESC开关信号异常", "0x405131": "转角传感器信号异常（CAN监控关闭时）", "0x505951": "车型配置不正确", "0x505955": "车型未配置", "0x505045": "车型配置数据不完整", "0x406201": "纵向加速度传感器电极错误", "0x406228": "纵向加速度传感器信号偏移错误", "0x406200": "纵向加速度传感器自检错误", "0x406254": "纵向加速度传感器未标定", "0x406301": "转角传感器信号异常（电气）", "0x406328": "转角传感器信号异常（信号偏移）", "0x406349": "转角传感器信号异常（通信）", "0x406364": "转角传感器信号异常（信号）", "0x406101": "横向加速度传感器异常（电气）", "0x406195": "横向加速度传感器异常（偏移）", "0x406128": "横向加速度传感器异常（偏移，车速静止时）", "0x406100": "横向加速度传感器异常（自检）", "0x406164": "横向加速度传感器异常（信号）", "0x406154": "横向加速度传感器异常（未标定）", "0x404401": "压力传感器异常（电气）", "0x404428": "压力传感器异常（压力值偏移）", "0x404449": "压力传感器异常（噪声）", "0x404427": "压力传感器异常（过高）", "0x404426": "压力传感器异常（过低）", "0x404464": "压力传感器异常（压力信号）", "0x404456": "压力传感器异常（型号配置）", "0x404425": "压力传感器异常（通信）", "0x404461": "压力传感器异常（温度信号）", "0x404496": "压力传感器异常（工作状态）", "0x405128": "转角传感器异常（偏移）", "0x405164": "转角传感器异常（信号）", "0x405186": "转角传感器异常（内部故障）", "0x405154": "转角传感器异常（未标定）", "0x403185": "左前轮超速", "0x403485": "右前轮超速", "0x403785": "左后轮超速", "0x403a85": "右后轮超速", "0x505022": "减速度过大", "0x505a16": "轮速信号不正确（HSA工作期间）", "0x505b49": "阀电流过大", "0x505c13": "LK30断路", "0x505d04": "地线损耗故障", "0x403119": "左前轮传感器过电流", "0x403419": "右前轮传感器过电流", "0x403719": "左后轮传感器过电流", "0x403a19": "右后轮传感器过电流", "0x505e29": "倒挡信号故障", "0x505f4a": "HECU不匹配_可修复", "0x50504a": "HECU不匹配_不可修复", "0x406385": "转角传感器信号过高", "0x406384": "转角传感器信号过低", "0x406185": "横向加速度传感器信号过高", "0x406184": "横向加速度传感器信号过低", "0x406222": "纵向加速度传感器信号过高", "0x406221": "纵向加速度传感器信号过低", "0x406149": "横向加速度传感器通信故障", "0x406249": "纵向加速度传感器通信故障", "0x405185": "转角传感器信号过高", "0x405184": "转角传感器信号过低", "0x405127": "转角传感器信号变化率异常", "0xc07300": "CAN 总线关闭", "0xd30087": "VCU通信丢失", "0xd30587": "MCU通信丢失", "0xd30687": "BCM通信丢失", "0xd31287": "ICU通信丢失", "0xd31387": "IVI通信丢失", "0xd30c87": "GW通信丢失", "0xd30e87": "ACU通信丢失", "0xd31087": "EPS通信丢失", "0xd36387": "ADAS通信丢失", "0xd2a086": "刹车开关信号信号错误", "0xd2a186": "加速踏板故障信号错误", "0xd2a286": "真空度传感器值错误", "0xd2a386": "驾驶员请求扭矩值信号错误", "0xd2a486": "电机转速错误信号错误", "0xd2a586": "实际扭矩反馈错误信号错误", "0xd2a686": "室外温度信号错误", "0xd2a786": "主驾安全带锁扣信号错误", "0xd2a886": "实际方向盘转角信号有效性信号错误", "0xd2a986": "方向盘转角速度信号有效性信号错误", "0xd2aa86": "方向盘转角传感器错误标志信号错误", "0xd2ab86": "ACC工作模式信号错误", "0xd2aac86": "AEB请求目标减速度值信号错误", "0x506061": "左前轮轮速传感器空气间隙过大", "0x506161": "右前轮轮速传感器空气间隙过大", "0x506261": "右后轮轮速传感器空气间隙过大", "0x506361": "左后轮轮速传感器空气间隙过大", "0x40314a": "左前轮轮速传感器类型错误", "0x40344a": "右前轮轮速传感器类型错误", "0x403a4a": "右后轮轮速传感器类型错误", "0x40374a": "左后轮轮速传感器类型错误", "0x506686": "引擎扭矩要求不能调整错误", "0x506797": "电子手刹按键卡滞", "0x506813": "未安装开关", "0x506901": "开关干扰故障", "0x506a02": "开关未知故障", "0x506b01": "开关单独故障", "0x506c12": "检测到开关短路", "0x506d49": "开关唤醒故障", "0x506e12": "开关灯内部短路", "0x506f12": "ipbX开关灯断线", "0x50701d": "左执行器激活时H桥监控故障", "0x50711d": "右执行器激活时H桥监控故障", "0x507201": "左执行器被动测试内部故障", "0x507301": "右执行器被动测试内部故障", "0x507413": "左执行器被动测试外部故障", "0x507513": "右执行器被动测试外部故障", "0x50761d": "左执行器被动测试短路故障", "0x50771d": "右执行器被动测试短路故障", "0x507849": "IPEX看门狗FMON禁止监视", "0x507962": "开关信号有效监控", "0x507a49": "IPEX带隙错误监控", "0x507b4b": "IPEX MPO传感器温度监控", "0x507c49": "IPEX热传感器监控", "0x507d4b": "REC FET温度监控", "0x507e4b": "REC FET温度警告监控", "0x507f49": "FET过载监控故障", "0x508094": "IPB power latch监控故障", "0x508177": "IPB执行器状态监控故障", "0x508249": "safety consent故障", "0x50839a": "RBT 检查模式", "0x508494": "IPB执行器状态未知错误", "0x508507": "左执行器无法拉起left actuator cannot be pulled up", "0x508607": "右执行器无法拉起right actuator cannot be pulled up", "0x508707": "左执行器无法达到目标夹紧力left actuator cannot reach the target clamping force", "0x508807": "右执行器无法达到目标夹紧力right actuator cannot reach the target clamping force", "0x508918": "左电机空载电流大left motor has a large no-load current", "0x508a19": "右电机空载电流大right motor has a large no-load current", "0x508b16": "低电压动作禁止Low voltage operation prohibited", "0x508c17": "高电压动作禁止High voltage operation prohibited", "0x508d07": "制动状态不一致Inconsistent braking status", "0x508e07": "制动状态未知Unknown braking status", "0x508f07": "驱动控制引起的左执行器状态未知", "0x509007": "驱动控制引起的右执行器状态未知", "0x509148": "软件故障（PBC模块）", "0x509254": "装配检测未进行", "0x509353": "维修模式进行", "0x509446": "匹配参数无效", "0x503124": "测试用FW", "0x503a00": "测试用FW", "0x503b54": "测试用FW", "0x503224": "测试用FW", "0x503229": "测试用FW", "0xd31187": "测试用FW", "0xd31487": "测试用FW", "0xd28087": "测试用FW"}